<?xml version="1.0" encoding="utf-8"?>
<!DOCTYPE hibernate-mapping PUBLIC "-//Hibernate/Hibernate Mapping DTD 3.0//EN"
"http://hibernate.sourceforge.net/hibernate-mapping-3.0.dtd">
<!-- 
    Mapping file autogenerated by MyEclipse Persistence Tools
-->
	<hibernate-mapping package="cn.honry.base.bean.model">
		<class name="InpatientAccount" table="T_INPATIENT_ACCOUNT">
		<id name="id" type="java.lang.String" >
			<column name="ACCOUNT_ID " />
			<generator class="uuid" />
		</id>
        <property name="inpatientNo" type="java.lang.String">
            <column name="INPATIENT_NO" >
                <comment>住院流水号</comment>
            </column>
        </property>
        
        <many-to-one name="idcard" class="PatientIdcard" fetch="select">
            <column name="IDCARD_ID" >
            </column>
        </many-to-one>
        
        <property name="medicalrecordId" type="java.lang.String">
            <column name="MEDICALRECORD_ID" >
                <comment>病历号</comment>
            </column>
        </property>
        <property name="accountRefid" type="java.lang.String">
            <column name="ACCOUNT_REFID" >
                <comment>参考编号</comment>
            </column>
        </property>
        <property name="accountName" type="java.lang.String">
            <column name="ACCOUNT_NAME" >
                <comment>名称</comment>
            </column>
        </property>
        <property name="accountType" type="java.lang.String">
            <column name="ACCOUNT_TYPE" >
                <comment>类型:从编码表里读取</comment>
            </column>
        </property>
        <property name="accountState" type="java.lang.Integer">
            <column name="ACCOUNT_STATE">
                <comment>1正常2注销3结清</comment>
            </column>
        </property>
        <property name="accountBalance" type="java.lang.Double">
            <column name="ACCOUNT_BALANCE" precision="18" scale="4">
                <comment>金额</comment>
            </column>
        </property>
        <property name="accountDaylimit" type="java.lang.Double">
            <column name="ACCOUNT_DAYLIMIT" precision="18" scale="4">
                <comment>单日消费限额</comment>
            </column>
        </property>
        <property name="accountFrozencapital" type="java.lang.Double">
            <column name="ACCOUNT_FROZENCAPITAL" precision="18" scale="4">
                <comment>冻结金额</comment>
            </column>
        </property>
        <property name="accountFrozentime" type="java.util.Date">
            <column name="ACCOUNT_FROZENTIME" length="7">
                <comment>冻结时间</comment>
            </column>
        </property>
        <property name="accountUnfrozentime" type="java.util.Date">
            <column name="ACCOUNT_UNFROZENTIME" length="7">
                <comment>解冻时间</comment>
            </column>
        </property>
        <property name="accountRemark" type="java.lang.String">
            <column name="ACCOUNT_REMARK" >
                <comment>备注</comment>
            </column>
        </property>
        <property name="createUser" type="java.lang.String">
            <column name="CREATEUSER"  />
        </property>
        <property name="createDept" type="java.lang.String">
            <column name="CREATEDEPT" />
        </property>        
        <property name="createTime" type="java.sql.Timestamp">
            <column name="CREATETIME" length="19" />
        </property>
        <property name="updateUser" type="java.lang.String">
            <column name="UPDATEUSER" />
        </property>      
        <property name="updateTime" type="java.sql.Timestamp">
            <column name="UPDATETIME" length="19" />
        </property>
        <property name="deleteUser" type="java.lang.String">
            <column name="DELETEUSER"  />
        </property>      
        <property name="deleteTime" type="java.sql.Timestamp">
            <column name="DELETETIME" length="19" />
        </property>        
        <property name="del_flg" type="java.lang.Integer">
            <column name="DEL_FLG" />
        </property>
        <property name="stop_flg" type="java.lang.Integer">
            <column name="STOP_FLG" />
        </property>
    </class>
</hibernate-mapping>
