<?xml version="1.0" encoding="utf-8"?>
<!DOCTYPE hibernate-mapping PUBLIC "-//Hibernate/Hibernate Mapping DTD 3.0//EN"
"http://hibernate.sourceforge.net/hibernate-mapping-3.0.dtd">
<!-- 
    Mapping file autogenerated by MyEclipse Persistence Tools
-->
<hibernate-mapping>
    <class name="cn.honry.base.bean.model.InpAccess" table="T_INP_ACCESS">
        <comment>患者阶段性评估</comment>
        <id name="id" type="java.lang.String">
            <column name="ID" length="50" />
            <generator class="uuid" />
        </id>
        <property name="stageId" type="java.lang.String">
            <column name="STAGE_ID"/>
        </property>
        <property name="inpatientNo" type="java.lang.String">
            <column name="INPATIENT_NO"/>
        </property>
        <property name="accessDate" type="java.util.Date">
            <column name="ACCESS_DATE">
                <comment>评估时间</comment>
            </column>
        </property>
        <property name="accessUser" type="java.lang.String">
            <column name="ACCESS_USER">
                <comment>评估人</comment>
            </column>
        </property>
        <property name="accessResult" type="java.lang.String">
            <column name="ACCESS_RESULT">
                <comment>角色标志</comment>
            </column>
        </property>
        <property name="roleFlag" type="java.lang.String">
            <column name="ROLE_FLAG">
                <comment>评估结果</comment>
            </column>
        </property>
        <property name="accessCheckUser" type="java.lang.String">
            <column name="ACCESS_CHECK_USER">
                <comment>评估审核人</comment>
            </column>
        </property>
        <property name="accessCheckDate" type="java.util.Date">
            <column name="ACCESS_CHECK_DATE">
                <comment>评估审核时</comment>
            </column>
        </property>
        <property name="accessCheckInfo" type="java.lang.String">
            <column name="ACCESS_CHECK_INFO" length="500">
                <comment>评估审核信息</comment>
            </column>
        </property>
        <property name="days" type="java.lang.String">
            <column name="DAYS">
                <comment>天数</comment>
            </column>
        </property>
            <property name="createUser" type="java.lang.String">
	            <column name="CREATE_USER">
	                <comment>创建人</comment>
	            </column>
	        </property>
	        <property name="createTime" type="java.util.Date">
	            <column name="CREATE_DATE">
	                <comment>创建时间</comment>
	            </column>
	        </property>
	        <property name="updateUser" type="java.lang.String">
	            <column name="UPDATE_USER">
	            </column>
	        </property>
	        <property name="updateTime" type="java.util.Date">
	            <column name="UPDATE_DATE">
	            </column>
	        </property>
	        <property name="hospitalId" type="java.lang.String">
	            <column name="HOSPITAL_ID">
	                <comment>所属医院</comment>
	            </column>
	        </property>
	        <property name="areaCode" type="java.lang.String">
	            <column name="AREA_CODE">
	                <comment>所属院区</comment>
	            </column>
	        </property>
	                <property name="del_flg" type="java.lang.Integer">
	            <column name="DELECT_FLAG" />
	        </property>
	        <property name="stop_flg" type="java.lang.Integer">
	            <column name="STOP_FLAG" />
	        </property>
    </class>
</hibernate-mapping>
