<?xml version="1.0" encoding="utf-8"?>
<!DOCTYPE hibernate-mapping PUBLIC "-//Hibernate/Hibernate Mapping DTD 3.0//EN"
"http://hibernate.sourceforge.net/hibernate-mapping-3.0.dtd">
<!-- 
    Mapping file autogenerated by MyEclipse Persistence Tools
-->
<hibernate-mapping package="cn.honry.base.bean.model">
	<class name="OutpatientMedicalrecord" table="T_OUTPATIENT_MEDICALRECORD">        
        <id name="id" type="java.lang.String">
            <column name="ID" />
            <generator class="uuid" />
        </id>
        <property name="clinicCode" type="java.lang.String">
            <column name="CLINIC_CODE" >
                <comment>就诊号或住院号</comment>
            </column>
        </property>
        <property name="pasource" type="java.lang.Integer">
            <column name="PASOURCE" precision="1" scale="0">
                <comment>来源1门诊2住院</comment>
            </column>
        </property>
        <property name="patientNo" type="java.lang.String">
            <column name="PATIENT_NO" >
                <comment>病历号</comment>
            </column>
        </property>
        <property name="name" type="java.lang.String">
            <column name="NAME" >
                <comment>患者姓名</comment>
            </column>
        </property>
        <property name="sex" type="java.lang.String">
            <column name="SEX" >
                <comment>性别(编码表)</comment>
            </column>
        </property>
        <property name="age" type="java.lang.Integer">
            <column name="AGE" precision="22" scale="0">
                <comment>年龄</comment>
            </column>
        </property>
        <property name="birthday" type="java.util.Date">
            <column name="BIRTHDAY" length="7">
                <comment>出生日期</comment>
            </column>
        </property>
        <property name="weight" type="java.lang.Double">
            <column name="WEIGHT" precision="18">
                <comment>体重</comment>
            </column>
        </property>
        <property name="telephone" type="java.lang.String">
            <column name="TELEPHONE" >
                <comment>联系电话</comment>
            </column>
        </property>
        <property name="itemCode" type="java.lang.String">
            <column name="ITEM_CODE" >
                <comment>项目编码</comment>
            </column>
        </property>
        <property name="checkpart" type="java.lang.String">
            <column name="CHECKPART" >
                <comment>检查部位</comment>
            </column>
        </property>
        <property name="applyDate" type="java.util.Date">
            <column name="APPLY_DATE" length="7">
                <comment>申请日期</comment>
            </column>
        </property>
        <property name="applyDoc" type="java.lang.String">
            <column name="APPLY_DOC" >
                <comment>申请医生编码</comment>
            </column>
        </property>
        <property name="maindesc" type="java.lang.String">
            <column name="MAINDESC" >
                <comment>主诉</comment>
            </column>
        </property>
        <property name="heredityHis" type="java.lang.String">
            <column name="HEREDITYHIS" >
                <comment>家族遗传史</comment>
            </column>
        </property>
        <property name="diagnoseType" type="java.lang.Integer">
            <column name="DIAGNOSE_TYPE" precision="1" scale="0">
                <comment>1 初诊2复诊3急症</comment>
            </column>
        </property>
 		<property name="diagnoseDate" type="java.util.Date">
            <column name="DIAGNOSE_DATE" length="7">
                <comment>就诊时间</comment>
            </column>
        </property>
        <property name="allergichistory" type="java.lang.String">
            <column name="ALLERGICHISTORY" >
                <comment>过敏史</comment>
            </column>
        </property>
        <property name="historyspecil" type="java.lang.String">
            <column name="HISTORYSPECIL" >
                <comment>病史和特征</comment>
            </column>
        </property>
        <property name="presentillness" type="java.lang.String">
            <column name="PRESENTILLNESS" >
                <comment>现病史</comment>
            </column>
        </property>
        <property name="temperature" type="java.lang.Double">
            <column name="TEMPERATURE" precision="18">
                <comment>体温</comment>
            </column>
        </property>
        <property name="pulse" type="java.lang.Double">
            <column name="PULSE" precision="18">
                <comment>脉搏</comment>
            </column>
        </property>
        <property name="breathing" type="java.lang.Double">
            <column name="BREATHING" precision="18">
                <comment>呼吸</comment>
            </column>
        </property>
        <property name="bloodPressure" type="java.lang.String">
            <column name="BLOOD_PRESSURE" >
                <comment>血压</comment>
            </column>
        </property>
        <property name="physicalExamination" type="java.lang.String">
            <column name="PHYSICAL_EXAMINATION" >
                <comment>体格检查</comment>
            </column>
        </property>
        <property name="checkresult" type="java.lang.String">
            <column name="CHECKRESULT" >
                <comment>检查检验结果</comment>
            </column>
        </property>
        <property name="diagnose1" type="java.lang.String">
            <column name="DIAGNOSE1" >
                <comment>诊断1</comment>
            </column>
        </property>
        <property name="diagnose2" type="java.lang.String">
            <column name="DIAGNOSE2" >
                <comment>诊断2</comment>
            </column>
        </property>
        <property name="diagnose3" type="java.lang.String">
            <column name="DIAGNOSE3" >
                <comment>诊断3</comment>
            </column>
        </property>
        <property name="diagnose4" type="java.lang.String">
            <column name="DIAGNOSE4" >
                <comment>诊断4</comment>
            </column>
        </property>
        <property name="remark" type="java.lang.String">
            <column name="REMARK" >
                <comment>备注</comment>
            </column>
        </property>
        <property name="purpose" type="java.lang.String">
            <column name="PURPOSE" >
                <comment>检查目的要求</comment>
            </column>
        </property>
        <property name="address" type="java.lang.String">
            <column name="ADDRESS" >
                <comment>就诊地址</comment>
            </column>
        </property>
        <property name="advice" type="java.lang.String">
            <column name="ADVICE" >
                <comment>医嘱建议</comment>
            </column>
        </property>
       <property name="createUser" type="java.lang.String">
           <column name="CREATEUSER" />
        </property>
        <property name="createDept" type="java.lang.String">
            <column name="CREATEDEPT" />
        </property>        
        <property name="createTime" type="java.sql.Timestamp">
            <column name="CREATETIME" length="19" />
        </property>
        <property name="updateUser" type="java.lang.String">
            <column name="UPDATEUSER" />
        </property>      
        <property name="updateTime" type="java.sql.Timestamp">
            <column name="UPDATETIME" length="19" />
        </property>
        <property name="deleteUser" type="java.lang.String">
            <column name="DELETEUSER"  />
        </property>      
        <property name="deleteTime" type="java.sql.Timestamp">
            <column name="DELETETIME" length="19" />
        </property>        
        <property name="del_flg" type="java.lang.Integer">
            <column name="DEL_FLG" />
        </property>
        <property name="stop_flg" type="java.lang.Integer">
            <column name="STOP_FLG" />
        </property>
    </class>
</hibernate-mapping>
