<?xml version="1.0" encoding="utf-8"?>
<!DOCTYPE hibernate-mapping PUBLIC "-//Hibernate/Hibernate Mapping DTD 3.0//EN"
"http://hibernate.sourceforge.net/hibernate-mapping-3.0.dtd">
<!-- 
    Mapping file autogenerated by MyEclipse Persistence Tools
-->
<hibernate-mapping package="cn.honry.base.bean.model">
    <class name="PublicAddressBook" table="T_OA_PUBLIC_BOOK" >
        <comment>公共通讯录表</comment>
        <id name="id" type="java.lang.String">
            <column name="ID" />
            <generator class="uuid" />
        </id>
        <property name="name" type="java.lang.String">
            <column name="NODE_NAME">
                <comment>节点名称</comment>
            </column>
        </property>
        <property name="parentCode" type="java.lang.String">
            <column name="PARENT_CODE">
                <comment>父级节点</comment>
            </column>
        </property>
        <property name="nodeLevel" type="java.lang.Integer">
            <column name="NODE_LEVEL">
                <comment>层级</comment>
            </column>
        </property>
        <property name="path" type="java.lang.String">
            <column name="PATH">
                <comment>路径</comment>
            </column>
        </property>
        <property name="superPath" type="java.lang.String">
            <column name="SUPERPATH">
                <comment>父级路径</comment>
            </column>
        </property>
        <property name="order" type="java.lang.Integer">
            <column name="ORDER_ID">
                <comment>顺序</comment>
            </column>
        </property>
        <property name="nodeType" type="java.lang.String">
            <column name="NODE_TYPE">
                <comment>节点类型(00-院区，11-楼号，22-楼层，33-科室分类，44-科室，55-工作站)</comment>
            </column>
        </property>
        <property name="status" type="java.lang.Integer">
            <column name="STATUS">
                <comment>状态(0：普通；1：常用)</comment>
            </column>
        </property>
        <property name="phone" type="java.lang.String">
            <column name="PHONE">
                <comment>电话</comment>
            </column>
        </property>
        <property name="minPhone" type="java.lang.String">
            <column name="MIN_PHONE">
                <comment>分机电话</comment>
            </column>
        </property>
         <property name="officePhone" type="java.lang.String">
            <column name="OFFICE_PHONE">
                <comment>办公电话</comment>
            </column>
        </property>
         <property name="createUser" type="java.lang.String">
            <column name="CREATEUSER"/>
        </property>
        <property name="createDept" type="java.lang.String">
            <column name="CREATEDEPT" />
        </property>        
        <property name="createTime" type="java.sql.Timestamp">
            <column name="CREATETIME" length="19" />
        </property>
        <property name="updateUser" type="java.lang.String">
            <column name="UPDATEUSER" />
        </property>      
        <property name="updateTime" type="java.sql.Timestamp">
            <column name="UPDATETIME" length="19" />
        </property>
        <property name="deleteUser" type="java.lang.String">
            <column name="DELETEUSER"  />
        </property>      
        <property name="deleteTime" type="java.sql.Timestamp">
            <column name="DELETETIME" length="19" />
        </property>        
        <property name="del_flg" type="java.lang.Integer">
            <column name="DEL_FLG" />
        </property>
        <property name="stop_flg" type="java.lang.Integer">
            <column name="STOP_FLG" />
        </property>
         <property name="areaName" type="java.lang.String">
            <column name="AREA_NAME">
                <comment>院区名称</comment>
            </column>
        </property>
         <property name="buildingName" type="java.lang.String">
            <column name="BUILDING_NAME">
                <comment>楼名</comment>
            </column>
        </property>
         <property name="floorName" type="java.lang.String">
            <column name="FLOOR_NAME">
                <comment>楼层</comment>
            </column>
        </property>
         <property name="floorType" type="java.lang.String">
            <column name="FLOOR_TYPE">
                <comment>楼层类型</comment>
            </column>
        </property>
         <property name="floorDept" type="java.lang.String">
            <column name="FLOOR_DEPT">
                <comment>楼层科室</comment>
            </column>
        </property>
    </class>
</hibernate-mapping>
